{
  "timestamp": "2025-03-04 15:14:59",
  "config": {
    "network": "ethereum",
    "token_pair": [
      "USDC",
      "USDT"
    ],
    "dex": "sushiswap",
    "trade_count": 20,
    "gas_strategy": "dynamic",
    "parallel_execution": true,
    "max_workers": 4
  },
  "opportunities": [
    {
      "id": "ethereum_USDC-USDT_sushiswap_1741086899",
      "network": "ethereum",
      "token_pair": [
        "USDC",
        "USDT"
      ],
      "dex": "sushiswap",
      "expected_profit": 153.1560463817366,
      "confidence": 0.7364191994985793,
      "execution_time": 189.1372496375993,
      "price_impact": 0.004348227343146681,
      "slippage_tolerance": 0.002924625997292672,
      "timestamp": "2025-03-04 15:14:59"
    },
    {
      "id": "ethereum_USDC-USDT_sushiswap_1741086899",
      "network": "ethereum",
      "token_pair": [
        "USDC",
        "USDT"
      ],
      "dex": "sushiswap",
      "expected_profit": 102.26606055957694,
      "confidence": 0.57373397758164,
      "execution_time": 60.25257443642529,
      "price_impact": 0.0031448792183282896,
      "slippage_tolerance": 0.006745545140931657,
      "timestamp": "2025-03-04 15:14:59"
    },
    {
      "id": "ethereum_USDC-USDT_sushiswap_1741086899",
      "network": "ethereum",
      "token_pair": [
        "USDC",
        "USDT"
      ],
      "dex": "sushiswap",
      "expected_profit": 180.66759422869941,
      "confidence": 0.7067174410461019,
      "execution_time": 101.8209535860784,
      "price_impact": 0.004775390103481529,
      "slippage_tolerance": 0.005690015485464043,
      "timestamp": "2025-03-04 15:14:59"
    },
    {
      "id": "ethereum_USDC-USDT_sushiswap_1741086899",
      "network": "ethereum",
      "token_pair": [
        "USDC",
        "USDT"
      ],
      "dex": "sushiswap",
      "expected_profit": 68.74483966108048,
      "confidence": 0.8068046435791946,
      "execution_time": 118.4745144797368,
      "price_impact": 0.0030446923491027453,
      "slippage_tolerance": 0.0013086595452816547,
      "timestamp": "2025-03-04 15:14:59"
    },
    {
      "id": "ethereum_USDC-USDT_sushiswap_1741086899",
      "network": "ethereum",
      "token_pair": [
        "USDC",
        "USDT"
      ],
      "dex": "sushiswap",
      "expected_profit": 95.23581296203471,
      "confidence": 0.7035423922762789,
      "execution_time": 110.92613464844678,
      "price_impact": 0.0011028904006817543,
      "slippage_tolerance": 0.0050871801412099155,
      "timestamp": "2025-03-04 15:14:59"
    },
    {
      "id": "ethereum_USDC-USDT_sushiswap_1741086899",
      "network": "ethereum",
      "token_pair": [
        "USDC",
        "USDT"
      ],
      "dex": "sushiswap",
      "expected_profit": 91.23673830327361,
      "confidence": 0.6215056799552008,
      "execution_time": 94.55654232806783,
      "price_impact": 0.0012245240136303766,
      "slippage_tolerance": 0.004479115399908954,
      "timestamp": "2025-03-04 15:14:59"
    },
    {
      "id": "ethereum_USDC-USDT_sushiswap_1741086899",
      "network": "ethereum",
      "token_pair": [
        "USDC",
        "USDT"
      ],
      "dex": "sushiswap",
      "expected_profit": 186.6411697502916,
      "confidence": 0.7732887908448327,
      "execution_time": 152.55100372875435,
      "price_impact": 0.003506083391561667,
      "slippage_tolerance": 0.0012523873578171433,
      "timestamp": "2025-03-04 15:14:59"
    },
    {
      "id": "ethereum_USDC-USDT_sushiswap_1741086899",
      "network": "ethereum",
      "token_pair": [
        "USDC",
        "USDT"
      ],
      "dex": "sushiswap",
      "expected_profit": 176.0258507417591,
      "confidence": 0.6360620046387974,
      "execution_time": 113.7930617944193,
      "price_impact": 0.004945290754959916,
      "slippage_tolerance": 0.007923098487903815,
      "timestamp": "2025-03-04 15:14:59"
    },
    {
      "id": "ethereum_USDC-USDT_sushiswap_1741086899",
      "network": "ethereum",
      "token_pair": [
        "USDC",
        "USDT"
      ],
      "dex": "sushiswap",
      "expected_profit": 92.84266007610628,
      "confidence": 0.5074823493791696,
      "execution_time": 141.67992047157782,
      "price_impact": 0.003531518045603114,
      "slippage_tolerance": 0.003574530240765299,
      "timestamp": "2025-03-04 15:14:59"
    },
    {
      "id": "ethereum_USDC-USDT_sushiswap_1741086899",
      "network": "ethereum",
      "token_pair": [
        "USDC",
        "USDT"
      ],
      "dex": "sushiswap",
      "expected_profit": 153.5658918650264,
      "confidence": 0.6107105328619875,
      "execution_time": 164.75174298672084,
      "price_impact": 0.0020888017217053833,
      "slippage_tolerance": 0.0038812476887082822,
      "timestamp": "2025-03-04 15:14:59"
    },
    {
      "id": "ethereum_USDC-USDT_sushiswap_1741086899",
      "network": "ethereum",
      "token_pair": [
        "USDC",
        "USDT"
      ],
      "dex": "sushiswap",
      "expected_profit": 106.10462675395598,
      "confidence": 0.7376926352237069,
      "execution_time": 140.24615613503482,
      "price_impact": 0.0019938034055200183,
      "slippage_tolerance": 0.0020091424926645465,
      "timestamp": "2025-03-04 15:14:59"
    },
    {
      "id": "ethereum_USDC-USDT_sushiswap_1741086899",
      "network": "ethereum",
      "token_pair": [
        "USDC",
        "USDT"
      ],
      "dex": "sushiswap",
      "expected_profit": 171.682545039656,
      "confidence": 0.9767030889518953,
      "execution_time": 134.9845361196013,
      "price_impact": 0.00470692691831201,
      "slippage_tolerance": 0.0024211167801806844,
      "timestamp": "2025-03-04 15:14:59"
    },
    {
      "id": "ethereum_USDC-USDT_sushiswap_1741086899",
      "network": "ethereum",
      "token_pair": [
        "USDC",
        "USDT"
      ],
      "dex": "sushiswap",
      "expected_profit": 183.80612411209242,
      "confidence": 0.7187279857917498,
      "execution_time": 172.5748635153745,
      "price_impact": 0.003005620390753134,
      "slippage_tolerance": 0.003748392107604409,
      "timestamp": "2025-03-04 15:14:59"
    },
    {
      "id": "ethereum_USDC-USDT_sushiswap_1741086899",
      "network": "ethereum",
      "token_pair": [
        "USDC",
        "USDT"
      ],
      "dex": "sushiswap",
      "expected_profit": 153.7660484834281,
      "confidence": 0.8967559815644479,
      "execution_time": 175.42761118285557,
      "price_impact": 0.004071638180110469,
      "slippage_tolerance": 0.007560210829112747,
      "timestamp": "2025-03-04 15:14:59"
    },
    {
      "id": "ethereum_USDC-USDT_sushiswap_1741086899",
      "network": "ethereum",
      "token_pair": [
        "USDC",
        "USDT"
      ],
      "dex": "sushiswap",
      "expected_profit": 167.0253257447218,
      "confidence": 0.561013205635681,
      "execution_time": 151.51323773663657,
      "price_impact": 0.0016447599987056791,
      "slippage_tolerance": 0.006019721928971151,
      "timestamp": "2025-03-04 15:14:59"
    },
    {
      "id": "ethereum_USDC-USDT_sushiswap_1741086899",
      "network": "ethereum",
      "token_pair": [
        "USDC",
        "USDT"
      ],
      "dex": "sushiswap",
      "expected_profit": 44.86726211120721,
      "confidence": 0.9958246409717486,
      "execution_time": 128.34232709166426,
      "price_impact": 0.0024128290738349026,
      "slippage_tolerance": 0.0074520513969206625,
      "timestamp": "2025-03-04 15:14:59"
    },
    {
      "id": "ethereum_USDC-USDT_sushiswap_1741086899",
      "network": "ethereum",
      "token_pair": [
        "USDC",
        "USDT"
      ],
      "dex": "sushiswap",
      "expected_profit": 85.73179803357998,
      "confidence": 0.982165013028996,
      "execution_time": 161.0054426320985,
      "price_impact": 0.004940313548869595,
      "slippage_tolerance": 0.001575258621515788,
      "timestamp": "2025-03-04 15:14:59"
    },
    {
      "id": "ethereum_USDC-USDT_sushiswap_1741086899",
      "network": "ethereum",
      "token_pair": [
        "USDC",
        "USDT"
      ],
      "dex": "sushiswap",
      "expected_profit": 10.329816039204324,
      "confidence": 0.6126530244505726,
      "execution_time": 79.23597475597194,
      "price_impact": 0.0020104513905679516,
      "slippage_tolerance": 0.003994127988218623,
      "timestamp": "2025-03-04 15:14:59"
    },
    {
      "id": "ethereum_USDC-USDT_sushiswap_1741086899",
      "network": "ethereum",
      "token_pair": [
        "USDC",
        "USDT"
      ],
      "dex": "sushiswap",
      "expected_profit": 79.28682277629073,
      "confidence": 0.7128998505359662,
      "execution_time": 111.45211504306418,
      "price_impact": 0.0018819221927835264,
      "slippage_tolerance": 0.00852758345091055,
      "timestamp": "2025-03-04 15:14:59"
    },
    {
      "id": "ethereum_USDC-USDT_sushiswap_1741086899",
      "network": "ethereum",
      "token_pair": [
        "USDC",
        "USDT"
      ],
      "dex": "sushiswap",
      "expected_profit": 82.70326708000594,
      "confidence": 0.6236602340290469,
      "execution_time": 57.24874390478917,
      "price_impact": 0.0014115146991144126,
      "slippage_tolerance": 0.004317890562438598,
      "timestamp": "2025-03-04 15:14:59"
    }
  ],
  "predictions": [
    {
      "opportunity_id": "ethereum_USDC-USDT_sushiswap_1741086899",
      "network": "ethereum",
      "token_pair": [
        "USDC",
        "USDT"
      ],
      "dex": "sushiswap",
      "expected_profit": 159.77612886548607,
      "confidence": 0.7364191994985793,
      "execution_time": 189.1372496375993,
      "price_impact": 0.004348227343146681,
      "slippage_tolerance": 0.002924625997292672,
      "is_profitable": false,
      "timestamp": "2025-03-04 15:14:59"
    },
    {
      "opportunity_id": "ethereum_USDC-USDT_sushiswap_1741086899",
      "network": "ethereum",
      "token_pair": [
        "USDC",
        "USDT"
      ],
      "dex": "sushiswap",
      "expected_profit": 82.00816716132593,
      "confidence": 0.57373397758164,
      "execution_time": 60.25257443642529,
      "price_impact": 0.0031448792183282896,
      "slippage_tolerance": 0.006745545140931657,
      "is_profitable": true,
      "timestamp": "2025-03-04 15:14:59"
    },
    {
      "opportunity_id": "ethereum_USDC-USDT_sushiswap_1741086899",
      "network": "ethereum",
      "token_pair": [
        "USDC",
        "USDT"
      ],
      "dex": "sushiswap",
      "expected_profit": 175.52514116352023,
      "confidence": 0.7067174410461019,
      "execution_time": 101.8209535860784,
      "price_impact": 0.004775390103481529,
      "slippage_tolerance": 0.005690015485464043,
      "is_profitable": true,
      "timestamp": "2025-03-04 15:14:59"
    },
    {
      "opportunity_id": "ethereum_USDC-USDT_sushiswap_1741086899",
      "network": "ethereum",
      "token_pair": [
        "USDC",
        "USDT"
      ],
      "dex": "sushiswap",
      "expected_profit": 58.344847124515844,
      "confidence": 0.8068046435791946,
      "execution_time": 118.4745144797368,
      "price_impact": 0.0030446923491027453,
      "slippage_tolerance": 0.0013086595452816547,
      "is_profitable": true,
      "timestamp": "2025-03-04 15:14:59"
    },
    {
      "opportunity_id": "ethereum_USDC-USDT_sushiswap_1741086899",
      "network": "ethereum",
      "token_pair": [
        "USDC",
        "USDT"
      ],
      "dex": "sushiswap",
      "expected_profit": 105.69930485835484,
      "confidence": 0.7035423922762789,
      "execution_time": 110.92613464844678,
      "price_impact": 0.0011028904006817543,
      "slippage_tolerance": 0.0050871801412099155,
      "is_profitable": true,
      "timestamp": "2025-03-04 15:14:59"
    },
    {
      "opportunity_id": "ethereum_USDC-USDT_sushiswap_1741086899",
      "network": "ethereum",
      "token_pair": [
        "USDC",
        "USDT"
      ],
      "dex": "sushiswap",
      "expected_profit": 86.48169228936148,
      "confidence": 0.6215056799552008,
      "execution_time": 94.55654232806783,
      "price_impact": 0.0012245240136303766,
      "slippage_tolerance": 0.004479115399908954,
      "is_profitable": true,
      "timestamp": "2025-03-04 15:14:59"
    },
    {
      "opportunity_id": "ethereum_USDC-USDT_sushiswap_1741086899",
      "network": "ethereum",
      "token_pair": [
        "USDC",
        "USDT"
      ],
      "dex": "sushiswap",
      "expected_profit": 188.12236493722517,
      "confidence": 0.7732887908448327,
      "execution_time": 152.55100372875435,
      "price_impact": 0.003506083391561667,
      "slippage_tolerance": 0.0012523873578171433,
      "is_profitable": true,
      "timestamp": "2025-03-04 15:14:59"
    },
    {
      "opportunity_id": "ethereum_USDC-USDT_sushiswap_1741086899",
      "network": "ethereum",
      "token_pair": [
        "USDC",
        "USDT"
      ],
      "dex": "sushiswap",
      "expected_profit": 171.9492678521018,
      "confidence": 0.6360620046387974,
      "execution_time": 113.7930617944193,
      "price_impact": 0.004945290754959916,
      "slippage_tolerance": 0.007923098487903815,
      "is_profitable": true,
      "timestamp": "2025-03-04 15:14:59"
    },
    {
      "opportunity_id": "ethereum_USDC-USDT_sushiswap_1741086899",
      "network": "ethereum",
      "token_pair": [
        "USDC",
        "USDT"
      ],
      "dex": "sushiswap",
      "expected_profit": 100.99613470631733,
      "confidence": 0.5074823493791696,
      "execution_time": 141.67992047157782,
      "price_impact": 0.003531518045603114,
      "slippage_tolerance": 0.003574530240765299,
      "is_profitable": true,
      "timestamp": "2025-03-04 15:14:59"
    },
    {
      "opportunity_id": "ethereum_USDC-USDT_sushiswap_1741086899",
      "network": "ethereum",
      "token_pair": [
        "USDC",
        "USDT"
      ],
      "dex": "sushiswap",
      "expected_profit": 156.3208106227232,
      "confidence": 0.6107105328619875,
      "execution_time": 164.75174298672084,
      "price_impact": 0.0020888017217053833,
      "slippage_tolerance": 0.0038812476887082822,
      "is_profitable": true,
      "timestamp": "2025-03-04 15:14:59"
    },
    {
      "opportunity_id": "ethereum_USDC-USDT_sushiswap_1741086899",
      "network": "ethereum",
      "token_pair": [
        "USDC",
        "USDT"
      ],
      "dex": "sushiswap",
      "expected_profit": 89.49968580462662,
      "confidence": 0.7376926352237069,
      "execution_time": 140.24615613503482,
      "price_impact": 0.0019938034055200183,
      "slippage_tolerance": 0.0020091424926645465,
      "is_profitable": true,
      "timestamp": "2025-03-04 15:14:59"
    },
    {
      "opportunity_id": "ethereum_USDC-USDT_sushiswap_1741086899",
      "network": "ethereum",
      "token_pair": [
        "USDC",
        "USDT"
      ],
      "dex": "sushiswap",
      "expected_profit": 193.53023834976642,
      "confidence": 0.9767030889518953,
      "execution_time": 134.9845361196013,
      "price_impact": 0.00470692691831201,
      "slippage_tolerance": 0.0024211167801806844,
      "is_profitable": false,
      "timestamp": "2025-03-04 15:14:59"
    },
    {
      "opportunity_id": "ethereum_USDC-USDT_sushiswap_1741086899",
      "network": "ethereum",
      "token_pair": [
        "USDC",
        "USDT"
      ],
      "dex": "sushiswap",
      "expected_profit": 185.88926858741527,
      "confidence": 0.7187279857917498,
      "execution_time": 172.5748635153745,
      "price_impact": 0.003005620390753134,
      "slippage_tolerance": 0.003748392107604409,
      "is_profitable": true,
      "timestamp": "2025-03-04 15:14:59"
    },
    {
      "opportunity_id": "ethereum_USDC-USDT_sushiswap_1741086899",
      "network": "ethereum",
      "token_pair": [
        "USDC",
        "USDT"
      ],
      "dex": "sushiswap",
      "expected_profit": 152.14611530216993,
      "confidence": 0.8967559815644479,
      "execution_time": 175.42761118285557,
      "price_impact": 0.004071638180110469,
      "slippage_tolerance": 0.007560210829112747,
      "is_profitable": true,
      "timestamp": "2025-03-04 15:14:59"
    },
    {
      "opportunity_id": "ethereum_USDC-USDT_sushiswap_1741086899",
      "network": "ethereum",
      "token_pair": [
        "USDC",
        "USDT"
      ],
      "dex": "sushiswap",
      "expected_profit": 142.07024815159537,
      "confidence": 0.561013205635681,
      "execution_time": 151.51323773663657,
      "price_impact": 0.0016447599987056791,
      "slippage_tolerance": 0.006019721928971151,
      "is_profitable": true,
      "timestamp": "2025-03-04 15:14:59"
    },
    {
      "opportunity_id": "ethereum_USDC-USDT_sushiswap_1741086899",
      "network": "ethereum",
      "token_pair": [
        "USDC",
        "USDT"
      ],
      "dex": "sushiswap",
      "expected_profit": 37.26914871994685,
      "confidence": 0.9958246409717486,
      "execution_time": 128.34232709166426,
      "price_impact": 0.0024128290738349026,
      "slippage_tolerance": 0.0074520513969206625,
      "is_profitable": true,
      "timestamp": "2025-03-04 15:14:59"
    },
    {
      "opportunity_id": "ethereum_USDC-USDT_sushiswap_1741086899",
      "network": "ethereum",
      "token_pair": [
        "USDC",
        "USDT"
      ],
      "dex": "sushiswap",
      "expected_profit": 89.27547329908009,
      "confidence": 0.982165013028996,
      "execution_time": 161.0054426320985,
      "price_impact": 0.004940313548869595,
      "slippage_tolerance": 0.001575258621515788,
      "is_profitable": true,
      "timestamp": "2025-03-04 15:14:59"
    },
    {
      "opportunity_id": "ethereum_USDC-USDT_sushiswap_1741086899",
      "network": "ethereum",
      "token_pair": [
        "USDC",
        "USDT"
      ],
      "dex": "sushiswap",
      "expected_profit": 11.008530093541129,
      "confidence": 0.6126530244505726,
      "execution_time": 79.23597475597194,
      "price_impact": 0.0020104513905679516,
      "slippage_tolerance": 0.003994127988218623,
      "is_profitable": false,
      "timestamp": "2025-03-04 15:14:59"
    },
    {
      "opportunity_id": "ethereum_USDC-USDT_sushiswap_1741086899",
      "network": "ethereum",
      "token_pair": [
        "USDC",
        "USDT"
      ],
      "dex": "sushiswap",
      "expected_profit": 93.77572628775599,
      "confidence": 0.7128998505359662,
      "execution_time": 111.45211504306418,
      "price_impact": 0.0018819221927835264,
      "slippage_tolerance": 0.00852758345091055,
      "is_profitable": true,
      "timestamp": "2025-03-04 15:14:59"
    },
    {
      "opportunity_id": "ethereum_USDC-USDT_sushiswap_1741086899",
      "network": "ethereum",
      "token_pair": [
        "USDC",
        "USDT"
      ],
      "dex": "sushiswap",
      "expected_profit": 71.72948960532595,
      "confidence": 0.6236602340290469,
      "execution_time": 57.24874390478917,
      "price_impact": 0.0014115146991144126,
      "slippage_tolerance": 0.004317890562438598,
      "is_profitable": true,
      "timestamp": "2025-03-04 15:14:59"
    }
  ],
  "protected_trades": [
    {
      "opportunity_id": "ethereum_USDC-USDT_sushiswap_1741086899",
      "network": "ethereum",
      "token_pair": [
        "USDC",
        "USDT"
      ],
      "dex": "sushiswap",
      "expected_profit": 82.00816716132593,
      "confidence": 0.57373397758164,
      "execution_time": 60.25257443642529,
      "price_impact": 0.0031448792183282896,
      "slippage_tolerance": 0.006745545140931657,
      "is_profitable": true,
      "timestamp": "2025-03-04 15:14:59",
      "mev_protected": true,
      "protection_cost": 3.362271212109937,
      "protection_strategy": "gas_price_bump"
    },
    {
      "opportunity_id": "ethereum_USDC-USDT_sushiswap_1741086899",
      "network": "ethereum",
      "token_pair": [
        "USDC",
        "USDT"
      ],
      "dex": "sushiswap",
      "expected_profit": 175.52514116352023,
      "confidence": 0.7067174410461019,
      "execution_time": 101.8209535860784,
      "price_impact": 0.004775390103481529,
      "slippage_tolerance": 0.005690015485464043,
      "is_profitable": true,
      "timestamp": "2025-03-04 15:14:59",
      "mev_protected": true,
      "protection_cost": 2.876258382586161,
      "protection_strategy": "private_tx"
    },
    {
      "opportunity_id": "ethereum_USDC-USDT_sushiswap_1741086899",
      "network": "ethereum",
      "token_pair": [
        "USDC",
        "USDT"
      ],
      "dex": "sushiswap",
      "expected_profit": 58.344847124515844,
      "confidence": 0.8068046435791946,
      "execution_time": 118.4745144797368,
      "price_impact": 0.0030446923491027453,
      "slippage_tolerance": 0.0013086595452816547,
      "is_profitable": true,
      "timestamp": "2025-03-04 15:14:59",
      "mev_protected": true,
      "protection_cost": 1.2381789235194711,
      "protection_strategy": "flashbots"
    },
    {
      "opportunity_id": "ethereum_USDC-USDT_sushiswap_1741086899",
      "network": "ethereum",
      "token_pair": [
        "USDC",
        "USDT"
      ],
      "dex": "sushiswap",
      "expected_profit": 105.69930485835484,
      "confidence": 0.7035423922762789,
      "execution_time": 110.92613464844678,
      "price_impact": 0.0011028904006817543,
      "slippage_tolerance": 0.0050871801412099155,
      "is_profitable": true,
      "timestamp": "2025-03-04 15:14:59",
      "mev_protected": true,
      "protection_cost": 4.4900040925482045,
      "protection_strategy": "backrunning"
    },
    {
      "opportunity_id": "ethereum_USDC-USDT_sushiswap_1741086899",
      "network": "ethereum",
      "token_pair": [
        "USDC",
        "USDT"
      ],
      "dex": "sushiswap",
      "expected_profit": 86.48169228936148,
      "confidence": 0.6215056799552008,
      "execution_time": 94.55654232806783,
      "price_impact": 0.0012245240136303766,
      "slippage_tolerance": 0.004479115399908954,
      "is_profitable": true,
      "timestamp": "2025-03-04 15:14:59",
      "mev_protected": true,
      "protection_cost": 1.5437407101576452,
      "protection_strategy": "backrunning"
    },
    {
      "opportunity_id": "ethereum_USDC-USDT_sushiswap_1741086899",
      "network": "ethereum",
      "token_pair": [
        "USDC",
        "USDT"
      ],
      "dex": "sushiswap",
      "expected_profit": 188.12236493722517,
      "confidence": 0.7732887908448327,
      "execution_time": 152.55100372875435,
      "price_impact": 0.003506083391561667,
      "slippage_tolerance": 0.0012523873578171433,
      "is_profitable": true,
      "timestamp": "2025-03-04 15:14:59",
      "mev_protected": true,
      "protection_cost": 2.159095339393514,
      "protection_strategy": "private_tx"
    },
    {
      "opportunity_id": "ethereum_USDC-USDT_sushiswap_1741086899",
      "network": "ethereum",
      "token_pair": [
        "USDC",
        "USDT"
      ],
      "dex": "sushiswap",
      "expected_profit": 171.9492678521018,
      "confidence": 0.6360620046387974,
      "execution_time": 113.7930617944193,
      "price_impact": 0.004945290754959916,
      "slippage_tolerance": 0.007923098487903815,
      "is_profitable": true,
      "timestamp": "2025-03-04 15:14:59",
      "mev_protected": true,
      "protection_cost": 6.650400068331548,
      "protection_strategy": "time_delay"
    },
    {
      "opportunity_id": "ethereum_USDC-USDT_sushiswap_1741086899",
      "network": "ethereum",
      "token_pair": [
        "USDC",
        "USDT"
      ],
      "dex": "sushiswap",
      "expected_profit": 100.99613470631733,
      "confidence": 0.5074823493791696,
      "execution_time": 141.67992047157782,
      "price_impact": 0.003531518045603114,
      "slippage_tolerance": 0.003574530240765299,
      "is_profitable": true,
      "timestamp": "2025-03-04 15:14:59",
      "mev_protected": true,
      "protection_cost": 0.33492988493188497,
      "protection_strategy": "time_delay"
    },
    {
      "opportunity_id": "ethereum_USDC-USDT_sushiswap_1741086899",
      "network": "ethereum",
      "token_pair": [
        "USDC",
        "USDT"
      ],
      "dex": "sushiswap",
      "expected_profit": 156.3208106227232,
      "confidence": 0.6107105328619875,
      "execution_time": 164.75174298672084,
      "price_impact": 0.0020888017217053833,
      "slippage_tolerance": 0.0038812476887082822,
      "is_profitable": true,
      "timestamp": "2025-03-04 15:14:59",
      "mev_protected": true,
      "protection_cost": 5.460612129185591,
      "protection_strategy": "flashbots"
    },
    {
      "opportunity_id": "ethereum_USDC-USDT_sushiswap_1741086899",
      "network": "ethereum",
      "token_pair": [
        "USDC",
        "USDT"
      ],
      "dex": "sushiswap",
      "expected_profit": 89.49968580462662,
      "confidence": 0.7376926352237069,
      "execution_time": 140.24615613503482,
      "price_impact": 0.0019938034055200183,
      "slippage_tolerance": 0.0020091424926645465,
      "is_profitable": true,
      "timestamp": "2025-03-04 15:14:59",
      "mev_protected": true,
      "protection_cost": 1.3227285923845051,
      "protection_strategy": "private_tx"
    },
    {
      "opportunity_id": "ethereum_USDC-USDT_sushiswap_1741086899",
      "network": "ethereum",
      "token_pair": [
        "USDC",
        "USDT"
      ],
      "dex": "sushiswap",
      "expected_profit": 185.88926858741527,
      "confidence": 0.7187279857917498,
      "execution_time": 172.5748635153745,
      "price_impact": 0.003005620390753134,
      "slippage_tolerance": 0.003748392107604409,
      "is_profitable": true,
      "timestamp": "2025-03-04 15:14:59",
      "mev_protected": true,
      "protection_cost": 2.093188356048474,
      "protection_strategy": "flashbots"
    },
    {
      "opportunity_id": "ethereum_USDC-USDT_sushiswap_1741086899",
      "network": "ethereum",
      "token_pair": [
        "USDC",
        "USDT"
      ],
      "dex": "sushiswap",
      "expected_profit": 152.14611530216993,
      "confidence": 0.8967559815644479,
      "execution_time": 175.42761118285557,
      "price_impact": 0.004071638180110469,
      "slippage_tolerance": 0.007560210829112747,
      "is_profitable": true,
      "timestamp": "2025-03-04 15:14:59",
      "mev_protected": true,
      "protection_cost": 6.670222833427174,
      "protection_strategy": "private_tx"
    },
    {
      "opportunity_id": "ethereum_USDC-USDT_sushiswap_1741086899",
      "network": "ethereum",
      "token_pair": [
        "USDC",
        "USDT"
      ],
      "dex": "sushiswap",
      "expected_profit": 142.07024815159537,
      "confidence": 0.561013205635681,
      "execution_time": 151.51323773663657,
      "price_impact": 0.0016447599987056791,
      "slippage_tolerance": 0.006019721928971151,
      "is_profitable": true,
      "timestamp": "2025-03-04 15:14:59",
      "mev_protected": true,
      "protection_cost": 0.5552887907839616,
      "protection_strategy": "time_delay"
    },
    {
      "opportunity_id": "ethereum_USDC-USDT_sushiswap_1741086899",
      "network": "ethereum",
      "token_pair": [
        "USDC",
        "USDT"
      ],
      "dex": "sushiswap",
      "expected_profit": 37.26914871994685,
      "confidence": 0.9958246409717486,
      "execution_time": 128.34232709166426,
      "price_impact": 0.0024128290738349026,
      "slippage_tolerance": 0.0074520513969206625,
      "is_profitable": true,
      "timestamp": "2025-03-04 15:14:59",
      "mev_protected": true,
      "protection_cost": 0.12636395745248827,
      "protection_strategy": "backrunning"
    },
    {
      "opportunity_id": "ethereum_USDC-USDT_sushiswap_1741086899",
      "network": "ethereum",
      "token_pair": [
        "USDC",
        "USDT"
      ],
      "dex": "sushiswap",
      "expected_profit": 89.27547329908009,
      "confidence": 0.982165013028996,
      "execution_time": 161.0054426320985,
      "price_impact": 0.004940313548869595,
      "slippage_tolerance": 0.001575258621515788,
      "is_profitable": true,
      "timestamp": "2025-03-04 15:14:59",
      "mev_protected": true,
      "protection_cost": 1.1550061108550238,
      "protection_strategy": "gas_price_bump"
    },
    {
      "opportunity_id": "ethereum_USDC-USDT_sushiswap_1741086899",
      "network": "ethereum",
      "token_pair": [
        "USDC",
        "USDT"
      ],
      "dex": "sushiswap",
      "expected_profit": 93.77572628775599,
      "confidence": 0.7128998505359662,
      "execution_time": 111.45211504306418,
      "price_impact": 0.0018819221927835264,
      "slippage_tolerance": 0.00852758345091055,
      "is_profitable": true,
      "timestamp": "2025-03-04 15:14:59",
      "mev_protected": true,
      "protection_cost": 2.22730137275518,
      "protection_strategy": "private_tx"
    },
    {
      "opportunity_id": "ethereum_USDC-USDT_sushiswap_1741086899",
      "network": "ethereum",
      "token_pair": [
        "USDC",
        "USDT"
      ],
      "dex": "sushiswap",
      "expected_profit": 71.72948960532595,
      "confidence": 0.6236602340290469,
      "execution_time": 57.24874390478917,
      "price_impact": 0.0014115146991144126,
      "slippage_tolerance": 0.004317890562438598,
      "is_profitable": true,
      "timestamp": "2025-03-04 15:14:59",
      "mev_protected": true,
      "protection_cost": 1.3745687254226113,
      "protection_strategy": "backrunning"
    }
  ],
  "execution_results": [
    {
      "opportunity_id": "ethereum_USDC-USDT_sushiswap_1741086899",
      "network": "ethereum",
      "token_pair": [
        "USDC",
        "USDT"
      ],
      "dex": "sushiswap",
      "expected_profit": 82.00816716132593,
      "confidence": 0.57373397758164,
      "execution_time": 60.25257443642529,
      "price_impact": 0.0031448792183282896,
      "slippage_tolerance": 0.006745545140931657,
      "is_profitable": true,
      "timestamp": "2025-03-04 15:14:59",
      "mev_protected": true,
      "protection_cost": 3.362271212109937,
      "protection_strategy": "gas_price_bump",
      "gas_price": 29.29036574770856,
      "gas_used": 356692.9161640607,
      "gas_cost": 3.134299792218626e-05,
      "status": "success",
      "actual_profit": 77.19908405739447,
      "actual_gas_price": 31.855587253278863,
      "actual_gas_used": 349801.04029488954,
      "actual_gas_cost": 3.3429352681204704e-05,
      "net_profit": 73.83677941593186,
      "execution_timestamp": "2025-03-04 15:14:59"
    },
    {
      "opportunity_id": "ethereum_USDC-USDT_sushiswap_1741086899",
      "network": "ethereum",
      "token_pair": [
        "USDC",
        "USDT"
      ],
      "dex": "sushiswap",
      "expected_profit": 175.52514116352023,
      "confidence": 0.7067174410461019,
      "execution_time": 101.8209535860784,
      "price_impact": 0.004775390103481529,
      "slippage_tolerance": 0.005690015485464043,
      "is_profitable": true,
      "timestamp": "2025-03-04 15:14:59",
      "mev_protected": true,
      "protection_cost": 2.876258382586161,
      "protection_strategy": "private_tx",
      "gas_price": 39.22765224776364,
      "gas_used": 399357.94234361214,
      "gas_cost": 4.699762345391298e-05,
      "status": "success",
      "actual_profit": 166.7578945178635,
      "actual_gas_price": 41.831270510773116,
      "actual_gas_used": 402015.1975285401,
      "actual_gas_cost": 5.045041943177475e-05,
      "net_profit": 163.8815856848579,
      "execution_timestamp": "2025-03-04 15:14:59"
    },
    {
      "opportunity_id": "ethereum_USDC-USDT_sushiswap_1741086899",
      "network": "ethereum",
      "token_pair": [
        "USDC",
        "USDT"
      ],
      "dex": "sushiswap",
      "expected_profit": 58.344847124515844,
      "confidence": 0.8068046435791946,
      "execution_time": 118.4745144797368,
      "price_impact": 0.0030446923491027453,
      "slippage_tolerance": 0.0013086595452816547,
      "is_profitable": true,
      "timestamp": "2025-03-04 15:14:59",
      "mev_protected": true,
      "protection_cost": 1.2381789235194711,
      "protection_strategy": "flashbots",
      "gas_price": 38.525748908639116,
      "gas_used": 382204.21316739835,
      "gas_cost": 4.4174110644933504e-05,
      "status": "success",
      "actual_profit": 50.51867891873798,
      "actual_gas_price": 34.99448176841322,
      "actual_gas_used": 373310.6733400768,
      "actual_gas_cost": 3.919144065646015e-05,
      "net_profit": 49.280460803777856,
      "execution_timestamp": "2025-03-04 15:14:59"
    },
    {
      "opportunity_id": "ethereum_USDC-USDT_sushiswap_1741086899",
      "network": "ethereum",
      "token_pair": [
        "USDC",
        "USDT"
      ],
      "dex": "sushiswap",
      "expected_profit": 105.69930485835484,
      "confidence": 0.7035423922762789,
      "execution_time": 110.92613464844678,
      "price_impact": 0.0011028904006817543,
      "slippage_tolerance": 0.0050871801412099155,
      "is_profitable": true,
      "timestamp": "2025-03-04 15:14:59",
      "mev_protected": true,
      "protection_cost": 4.4900040925482045,
      "protection_strategy": "backrunning",
      "gas_price": 36.105792613822814,
      "gas_used": 257649.46281719385,
      "gas_cost": 2.7907914214621363e-05,
      "status": "failed",
      "actual_profit": 0,
      "actual_gas_price": 38.78171932809153,
      "actual_gas_used": 257360.8335497709,
      "actual_gas_cost": 2.9942686838312694e-05,
      "net_profit": -2.9942686838312694e-05,
      "execution_timestamp": "2025-03-04 15:14:59"
    },
    {
      "opportunity_id": "ethereum_USDC-USDT_sushiswap_1741086899",
      "network": "ethereum",
      "token_pair": [
        "USDC",
        "USDT"
      ],
      "dex": "sushiswap",
      "expected_profit": 86.48169228936148,
      "confidence": 0.6215056799552008,
      "execution_time": 94.55654232806783,
      "price_impact": 0.0012245240136303766,
      "slippage_tolerance": 0.004479115399908954,
      "is_profitable": true,
      "timestamp": "2025-03-04 15:14:59",
      "mev_protected": true,
      "protection_cost": 1.5437407101576452,
      "protection_strategy": "backrunning",
      "gas_price": 20.22575578783863,
      "gas_used": 355596.89237066935,
      "gas_cost": 2.1576647712010486e-05,
      "status": "success",
      "actual_profit": 83.5268084695332,
      "actual_gas_price": 20.83424688741351,
      "actual_gas_used": 346434.84002994,
      "actual_gas_cost": 2.1653126962756126e-05,
      "net_profit": 81.98304610624858,
      "execution_timestamp": "2025-03-04 15:14:59"
    },
    {
      "opportunity_id": "ethereum_USDC-USDT_sushiswap_1741086899",
      "network": "ethereum",
      "token_pair": [
        "USDC",
        "USDT"
      ],
      "dex": "sushiswap",
      "expected_profit": 188.12236493722517,
      "confidence": 0.7732887908448327,
      "execution_time": 152.55100372875435,
      "price_impact": 0.003506083391561667,
      "slippage_tolerance": 0.0012523873578171433,
      "is_profitable": true,
      "timestamp": "2025-03-04 15:14:59",
      "mev_protected": true,
      "protection_cost": 2.159095339393514,
      "protection_strategy": "private_tx",
      "gas_price": 23.71010704501209,
      "gas_used": 237088.7226086369,
      "gas_cost": 1.6864196976647876e-05,
      "status": "success",
      "actual_profit": 219.45461818656486,
      "actual_gas_price": 23.145828628353478,
      "actual_gas_used": 246332.55915903402,
      "actual_gas_cost": 1.7104713599636238e-05,
      "net_profit": 217.29550574245775,
      "execution_timestamp": "2025-03-04 15:14:59"
    },
    {
      "opportunity_id": "ethereum_USDC-USDT_sushiswap_1741086899",
      "network": "ethereum",
      "token_pair": [
        "USDC",
        "USDT"
      ],
      "dex": "sushiswap",
      "expected_profit": 171.9492678521018,
      "confidence": 0.6360620046387974,
      "execution_time": 113.7930617944193,
      "price_impact": 0.004945290754959916,
      "slippage_tolerance": 0.007923098487903815,
      "is_profitable": true,
      "timestamp": "2025-03-04 15:14:59",
      "mev_protected": true,
      "protection_cost": 6.650400068331548,
      "protection_strategy": "time_delay",
      "gas_price": 25.02163425788891,
      "gas_used": 150492.7688477902,
      "gas_cost": 1.1296725061699272e-05,
      "status": "success",
      "actual_profit": 173.63904822202008,
      "actual_gas_price": 25.7705375014355,
      "actual_gas_used": 165392.98600182045,
      "actual_gas_cost": 1.2786798444702933e-05,
      "net_profit": 166.9886353668901,
      "execution_timestamp": "2025-03-04 15:14:59"
    },
    {
      "opportunity_id": "ethereum_USDC-USDT_sushiswap_1741086899",
      "network": "ethereum",
      "token_pair": [
        "USDC",
        "USDT"
      ],
      "dex": "sushiswap",
      "expected_profit": 100.99613470631733,
      "confidence": 0.5074823493791696,
      "execution_time": 141.67992047157782,
      "price_impact": 0.003531518045603114,
      "slippage_tolerance": 0.003574530240765299,
      "is_profitable": true,
      "timestamp": "2025-03-04 15:14:59",
      "mev_protected": true,
      "protection_cost": 0.33492988493188497,
      "protection_strategy": "time_delay",
      "gas_price": 29.598542662329322,
      "gas_used": 135932.27383730537,
      "gas_cost": 1.2070191619082746e-05,
      "status": "success",
      "actual_profit": 108.17269290564363,
      "actual_gas_price": 29.677840199095492,
      "actual_gas_used": 139329.23055331063,
      "actual_gas_cost": 1.240497191827226e-05,
      "net_profit": 107.83775061573984,
      "execution_timestamp": "2025-03-04 15:14:59"
    },
    {
      "opportunity_id": "ethereum_USDC-USDT_sushiswap_1741086899",
      "network": "ethereum",
      "token_pair": [
        "USDC",
        "USDT"
      ],
      "dex": "sushiswap",
      "expected_profit": 156.3208106227232,
      "confidence": 0.6107105328619875,
      "execution_time": 164.75174298672084,
      "price_impact": 0.0020888017217053833,
      "slippage_tolerance": 0.0038812476887082822,
      "is_profitable": true,
      "timestamp": "2025-03-04 15:14:59",
      "mev_protected": true,
      "protection_cost": 5.460612129185591,
      "protection_strategy": "flashbots",
      "gas_price": 26.48807358213667,
      "gas_used": 278418.10189136013,
      "gas_cost": 2.2124277508491518e-05,
      "status": "failed",
      "actual_profit": 0,
      "actual_gas_price": 27.080424717855507,
      "actual_gas_used": 260851.63886239272,
      "actual_gas_cost": 2.1191919506226776e-05,
      "net_profit": -2.1191919506226776e-05,
      "execution_timestamp": "2025-03-04 15:14:59"
    },
    {
      "opportunity_id": "ethereum_USDC-USDT_sushiswap_1741086899",
      "network": "ethereum",
      "token_pair": [
        "USDC",
        "USDT"
      ],
      "dex": "sushiswap",
      "expected_profit": 89.49968580462662,
      "confidence": 0.7376926352237069,
      "execution_time": 140.24615613503482,
      "price_impact": 0.0019938034055200183,
      "slippage_tolerance": 0.0020091424926645465,
      "is_profitable": true,
      "timestamp": "2025-03-04 15:14:59",
      "mev_protected": true,
      "protection_cost": 1.3227285923845051,
      "protection_strategy": "private_tx",
      "gas_price": 35.27403974005811,
      "gas_used": 271375.5094650956,
      "gas_cost": 2.8717531516050892e-05,
      "status": "success",
      "actual_profit": 96.11877509974705,
      "actual_gas_price": 37.339746510638456,
      "actual_gas_used": 276036.59787478665,
      "actual_gas_cost": 3.0921409776910725e-05,
      "net_profit": 94.79601558595277,
      "execution_timestamp": "2025-03-04 15:14:59"
    },
    {
      "opportunity_id": "ethereum_USDC-USDT_sushiswap_1741086899",
      "network": "ethereum",
      "token_pair": [
        "USDC",
        "USDT"
      ],
      "dex": "sushiswap",
      "expected_profit": 185.88926858741527,
      "confidence": 0.7187279857917498,
      "execution_time": 172.5748635153745,
      "price_impact": 0.003005620390753134,
      "slippage_tolerance": 0.003748392107604409,
      "is_profitable": true,
      "timestamp": "2025-03-04 15:14:59",
      "mev_protected": true,
      "protection_cost": 2.093188356048474,
      "protection_strategy": "flashbots",
      "gas_price": 32.02236770494065,
      "gas_used": 381328.50156904344,
      "gas_cost": 3.663312448085384e-05,
      "status": "success",
      "actual_profit": 163.01483502766237,
      "actual_gas_price": 31.575150034314408,
      "actual_gas_used": 401672.5898934995,
      "actual_gas_cost": 3.8048616871676663e-05,
      "net_profit": 160.92160862299704,
      "execution_timestamp": "2025-03-04 15:14:59"
    },
    {
      "opportunity_id": "ethereum_USDC-USDT_sushiswap_1741086899",
      "network": "ethereum",
      "token_pair": [
        "USDC",
        "USDT"
      ],
      "dex": "sushiswap",
      "expected_profit": 152.14611530216993,
      "confidence": 0.8967559815644479,
      "execution_time": 175.42761118285557,
      "price_impact": 0.004071638180110469,
      "slippage_tolerance": 0.007560210829112747,
      "is_profitable": true,
      "timestamp": "2025-03-04 15:14:59",
      "mev_protected": true,
      "protection_cost": 6.670222833427174,
      "protection_strategy": "private_tx",
      "gas_price": 34.334234416770215,
      "gas_used": 375233.205045287,
      "gas_cost": 3.865003446894266e-05,
      "status": "success",
      "actual_profit": 172.121992666491,
      "actual_gas_price": 33.4405612806274,
      "actual_gas_used": 339928.68098741135,
      "actual_gas_cost": 3.410221766280712e-05,
      "net_profit": 165.45173573084617,
      "execution_timestamp": "2025-03-04 15:14:59"
    },
    {
      "opportunity_id": "ethereum_USDC-USDT_sushiswap_1741086899",
      "network": "ethereum",
      "token_pair": [
        "USDC",
        "USDT"
      ],
      "dex": "sushiswap",
      "expected_profit": 142.07024815159537,
      "confidence": 0.561013205635681,
      "execution_time": 151.51323773663657,
      "price_impact": 0.0016447599987056791,
      "slippage_tolerance": 0.006019721928971151,
      "is_profitable": true,
      "timestamp": "2025-03-04 15:14:59",
      "mev_protected": true,
      "protection_cost": 0.5552887907839616,
      "protection_strategy": "time_delay",
      "gas_price": 35.273559396501554,
      "gas_used": 110964.97638318132,
      "gas_cost": 1.1742389056150613e-05,
      "status": "success",
      "actual_profit": 122.72419679817287,
      "actual_gas_price": 33.69168698006589,
      "actual_gas_used": 119607.84741452377,
      "actual_gas_cost": 1.2089370466348854e-05,
      "net_profit": 122.16889591801844,
      "execution_timestamp": "2025-03-04 15:14:59"
    },
    {
      "opportunity_id": "ethereum_USDC-USDT_sushiswap_1741086899",
      "network": "ethereum",
      "token_pair": [
        "USDC",
        "USDT"
      ],
      "dex": "sushiswap",
      "expected_profit": 37.26914871994685,
      "confidence": 0.9958246409717486,
      "execution_time": 128.34232709166426,
      "price_impact": 0.0024128290738349026,
      "slippage_tolerance": 0.0074520513969206625,
      "is_profitable": true,
      "timestamp": "2025-03-04 15:14:59",
      "mev_protected": true,
      "protection_cost": 0.12636395745248827,
      "protection_strategy": "backrunning",
      "gas_price": 38.84428439102237,
      "gas_used": 139338.51387352168,
      "gas_cost": 1.623751457857648e-05,
      "status": "success",
      "actual_profit": 30.97921354621604,
      "actual_gas_price": 38.926641040532964,
      "actual_gas_used": 125900.30792733667,
      "actual_gas_cost": 1.4702628280740002e-05,
      "net_profit": 30.852834886135273,
      "execution_timestamp": "2025-03-04 15:14:59"
    },
    {
      "opportunity_id": "ethereum_USDC-USDT_sushiswap_1741086899",
      "network": "ethereum",
      "token_pair": [
        "USDC",
        "USDT"
      ],
      "dex": "sushiswap",
      "expected_profit": 89.27547329908009,
      "confidence": 0.982165013028996,
      "execution_time": 161.0054426320985,
      "price_impact": 0.004940313548869595,
      "slippage_tolerance": 0.001575258621515788,
      "is_profitable": true,
      "timestamp": "2025-03-04 15:14:59",
      "mev_protected": true,
      "protection_cost": 1.1550061108550238,
      "protection_strategy": "gas_price_bump",
      "gas_price": 36.55905347178662,
      "gas_used": 224606.86234083353,
      "gas_cost": 2.4634242871346246e-05,
      "status": "failed",
      "actual_profit": 0,
      "actual_gas_price": 33.33852413982185,
      "actual_gas_used": 206759.05207211061,
      "actual_gas_cost": 2.0679124945898225e-05,
      "net_profit": -2.0679124945898225e-05,
      "execution_timestamp": "2025-03-04 15:14:59"
    },
    {
      "opportunity_id": "ethereum_USDC-USDT_sushiswap_1741086899",
      "network": "ethereum",
      "token_pair": [
        "USDC",
        "USDT"
      ],
      "dex": "sushiswap",
      "expected_profit": 93.77572628775599,
      "confidence": 0.7128998505359662,
      "execution_time": 111.45211504306418,
      "price_impact": 0.0018819221927835264,
      "slippage_tolerance": 0.00852758345091055,
      "is_profitable": true,
      "timestamp": "2025-03-04 15:14:59",
      "mev_protected": true,
      "protection_cost": 2.22730137275518,
      "protection_strategy": "private_tx",
      "gas_price": 30.272976167762366,
      "gas_used": 153183.6684756377,
      "gas_cost": 1.3911976635160176e-05,
      "status": "success",
      "actual_profit": 103.6112861253384,
      "actual_gas_price": 28.871805264321665,
      "actual_gas_used": 155034.39831844647,
      "actual_gas_cost": 1.3428368872564395e-05,
      "net_profit": 101.38397132421434,
      "execution_timestamp": "2025-03-04 15:14:59"
    },
    {
      "opportunity_id": "ethereum_USDC-USDT_sushiswap_1741086899",
      "network": "ethereum",
      "token_pair": [
        "USDC",
        "USDT"
      ],
      "dex": "sushiswap",
      "expected_profit": 71.72948960532595,
      "confidence": 0.6236602340290469,
      "execution_time": 57.24874390478917,
      "price_impact": 0.0014115146991144126,
      "slippage_tolerance": 0.004317890562438598,
      "is_profitable": true,
      "timestamp": "2025-03-04 15:14:59",
      "mev_protected": true,
      "protection_cost": 1.3745687254226113,
      "protection_strategy": "backrunning",
      "gas_price": 23.21985504155894,
      "gas_used": 214575.7868142751,
      "gas_cost": 1.4947255995767767e-05,
      "status": "failed",
      "actual_profit": 0,
      "actual_gas_price": 21.362278487932254,
      "actual_gas_used": 211736.65109713405,
      "actual_gas_cost": 1.3569531920517373e-05,
      "net_profit": -1.3569531920517373e-05,
      "execution_timestamp": "2025-03-04 15:14:59"
    }
  ],
  "metrics": {
    "total_trades": 17,
    "successful_trades": 13,
    "success_rate": 0.7647058823529411,
    "total_profit": 1567.8391245413854,
    "total_gas_cost": 0.00041569669883680994,
    "net_profit": 1536.6787404208048,
    "avg_execution_time": 126.85982033539676
  }
}